LICENSE
MANIFEST.in
README.md
setup.py
dsgrid/__init__.py
dsgrid/adapter.py
dsgrid/build.py
dsgrid/hub.py
dsgrid/shell.py
dsgrid/utils.py
dsgrid.egg-info/PKG-INFO
dsgrid.egg-info/SOURCES.txt
dsgrid.egg-info/dependency_links.txt
dsgrid.egg-info/entry_points.txt
dsgrid.egg-info/requires.txt
dsgrid.egg-info/top_level.txt
dsgrid/files/chrome/Dockerfile
dsgrid/files/chrome/README.md
dsgrid/files/chrome/run.sh
dsgrid/files/firefox/Dockerfile
dsgrid/files/firefox/register-node.sh
dsgrid/files/phantomjs/Dockerfile
dsgrid/files/phantomjs/register-node.sh
dsgrid/files/selenium/Dockerfile
dsgrid/tests/__init__.py
dsgrid/tests/test_docker_usage.py
dsgrid/tests/test_shell.py