Metadata-Version: 1.0
Name: dsgrid
Version: 0.1.3
Summary: Build and Manage a Selenium Grid using Docker.
Home-page: https://github.com/brady-vitrano/dsgrid
Author: Brady Vitrano
Author-email: bjvitrano@gmail.com
License: Apache
Keywords: docker selenium grid firefox phantomjs chrome
Platform: UNKNOWN
